MANIFEST.in
README.rst
setup.cfg
setup.py
pyunsplash/__init__.py
pyunsplash/pyunsplash.py
pyunsplash.egg-info/PKG-INFO
pyunsplash.egg-info/SOURCES.txt
pyunsplash.egg-info/dependency_links.txt
pyunsplash.egg-info/requires.txt
pyunsplash.egg-info/top_level.txt
pyunsplash/examples/example_collections.py
pyunsplash/examples/example_iteration.py
pyunsplash/src/__init__.py
pyunsplash/src/collections.py
pyunsplash/src/liblogging.py
pyunsplash/src/photos.py
pyunsplash/src/rest.py
pyunsplash/src/search.py
pyunsplash/src/settings.py
pyunsplash/src/stats.py
pyunsplash/src/unobject.py
pyunsplash/src/unpage.py
pyunsplash/src/users.py
pyunsplash/tests/documentation_test.py
pyunsplash/tests/test_collections.py
pyunsplash/tests/test_photos.py
pyunsplash/tests/test_search.py
pyunsplash/tests/test_stats.py
pyunsplash/tests/test_users.py
pyunsplash/tests/resources/resource__collections_curated_page_2.json
pyunsplash/tests/resources/resource__collections_featured_page_2.json
pyunsplash/tests/resources/resource__collections_page_2.json
pyunsplash/tests/resources/resource__photos_curated_page_2.json
pyunsplash/tests/resources/resource__photos_page_2.json
pyunsplash/tests/resources/resource__photos_random_count_2.json
pyunsplash/tests/resources/resource__search_collections_query_tree.json
pyunsplash/tests/resources/resource__search_photos_query_blue.json
pyunsplash/tests/resources/resource__search_users_query_ventura.json
pyunsplash/tests/resources/resource__stats_total.json
pyunsplash/tests/resources/resource__users_salvoventura.json
pyunsplash/tests/resources/resource__users_salvoventura_statistics.json
pyunsplash/tests/resources/resource_download.py